giga_task_solver/__init__.py
giga_task_solver/client.py
giga_task_solver/exceptions.py
giga_task_solver-0.1.0.dist-info/licenses/LICENSE
giga_task_solver-0.1.0.dist-info/METADATA
giga_task_solver-0.1.0.dist-info/WHEEL
giga_task_solver-0.1.0.dist-info/top_level.txt
giga_task_solver-0.1.0.dist-info/RECORD
